LiDARtoolkit/__init__.py
LiDARtoolkit-0.5.dist-info/LICENSE
LiDARtoolkit-0.5.dist-info/METADATA
LiDARtoolkit-0.5.dist-info/WHEEL
LiDARtoolkit-0.5.dist-info/top_level.txt
LiDARtoolkit-0.5.dist-info/RECORD
