Metadata-Version: 2.1
Name: LiDARtoolkit
Version: 0.5
Summary: A toolkit to handle LIDAR point cloud data.
Home-page: https://github.com/Ekan5h/LIDARtoolkit
Author: Ekan5h
Author-email: ekanshmahendru@gmail.com
License: UNKNOWN
Platform: UNKNOWN
Classifier: Programming Language :: Python :: 3
Classifier: Operating System :: OS Independent
